InterpretME/__init__.py
InterpretME/classification.py
InterpretME/dtreeviz_lib.py
InterpretME/federated_query_engine.py
InterpretME/pipeline.py
InterpretME/plots.py
InterpretME/preprocessing_data.py
InterpretME/sampling_strategy.py
InterpretME/semantification.py
InterpretME/shacl_api_config.json
InterpretME/upload.py
InterpretME/utils.py
InterpretME/mappings/classes.ttl
InterpretME/mappings/cross_validation.ttl
InterpretME/mappings/definition_feature.ttl
InterpretME/mappings/endpoint.ttl
InterpretME/mappings/entity_alignment.ttl
InterpretME/mappings/imp_features.ttl
InterpretME/mappings/lime_features.ttl
InterpretME/mappings/model_details.ttl
InterpretME/mappings/precision_recall.ttl
InterpretME/mappings/prediction_probabilities.ttl
InterpretME/mappings/sampling_strategy.ttl
InterpretME/mappings/shacl_validation_results.ttl
InterpretME-1.3.2.dist-info/LICENSE
InterpretME-1.3.2.dist-info/METADATA
InterpretME-1.3.2.dist-info/WHEEL
InterpretME-1.3.2.dist-info/top_level.txt
InterpretME-1.3.2.dist-info/RECORD
