Metadata-Version: 2.1
Name: InterpretME
Version: 1.3.2
Summary: An interpretable machine learning pipeline over knowledge graphs
Home-page: https://github.com/SDM-TIB/InterpretME
Download-URL: https://github.com/SDM-TIB/InterpretME/archive/refs/tags/v1.3.2.tar.gz
Author: Yashraj Chudasama, Disha Purohit, Philipp Rohde, Julian Gercke
Author-email: yashraj.chudasama@tib.eu
Classifier: Programming Language :: Python :: 3
Classifier: Programming Language :: Python :: 3 :: Only
Classifier: Programming Language :: Python :: 3.8
Classifier: Programming Language :: Python :: 3.9
Classifier: Operating System :: OS Independent
Classifier: License :: OSI Approved :: MIT License
Classifier: Development Status :: 5 - Production/Stable
Classifier: Intended Audience :: Science/Research
Classifier: Operating System :: OS Independent
Requires-Python: >=3.8, <3.10
License-File: LICENSE
Requires-Dist: pandas (<2.0.0,>=1.4.0)
Requires-Dist: imbalanced-learn (>=0.9.0)
Requires-Dist: lime (>=0.2.0)
Requires-Dist: pydotplus (>=2.0.2)
Requires-Dist: svglib (>=1.2.1)
Requires-Dist: colour (>=0.1.5)
Requires-Dist: matplotlib (<=3.3.4)
Requires-Dist: rdflib (<=6.1.1)
Requires-Dist: seaborn (>=0.11.2)
Requires-Dist: numpy (>=1.23.5)
Requires-Dist: dtreeviz (>=2.2.0)
Requires-Dist: python-slugify (>=6.0.0)
Requires-Dist: requests (>=2.31.0)
Requires-Dist: rdfizer (>=4.5.5)
Requires-Dist: DeTrusty (>=0.12.3)
Requires-Dist: validating-models (>=0.9.5)
Requires-Dist: optuna (>=3.2.0)
Requires-Dist: scikit-learn (<1.3.0,>=1.2.0)
